squaddata/cli.py
squaddata/dataframe.py
squaddata/datasets.py
squaddata/logging.py
squaddata/reports.py
squaddata/templates/report.txt.jinja
squaddata/templates/report_full.txt.jinja
squaddata/templates/blocks/base.jinja
squaddata/templates/blocks/signature.jinja
squaddata-0.0.2.dist-info/LICENSE
squaddata-0.0.2.dist-info/METADATA
squaddata-0.0.2.dist-info/WHEEL
squaddata-0.0.2.dist-info/entry_points.txt
squaddata-0.0.2.dist-info/top_level.txt
squaddata-0.0.2.dist-info/RECORD
