Metadata-Version: 2.1
Name: squaddata
Version: 0.0.2
Summary: squad data
Home-page: https://gitlab.com/linaro/lkft/reports/squaddata
Author: LKFT
Author-email: lkft@linaro.org
License: MIT
Platform: UNKNOWN
Requires-Python: >=3.6, <4
Requires-Dist: jinja2
Requires-Dist: pandas
Requires-Dist: requests
Requires-Dist: requests-cache
Requires-Dist: squad-client
